bkash_client/__init__.py
bkash_client/client.py
bkash_client/dataclasses/__init__.py
bkash_client/dataclasses/agreement.py
bkash_client/dataclasses/base.py
bkash_client/dataclasses/checkout.py
bkash_client/dataclasses/disbursement.py
bkash_client/dataclasses/refund.py
bkash_client/dataclasses/webhooks.py
bkash_client-0.2.6.dist-info/AUTHORS.rst
bkash_client-0.2.6.dist-info/LICENSE
bkash_client-0.2.6.dist-info/METADATA
bkash_client-0.2.6.dist-info/WHEEL
bkash_client-0.2.6.dist-info/top_level.txt
bkash_client-0.2.6.dist-info/RECORD
