Metadata-Version: 2.1
Name: bkash-client
Version: 0.2.6
Summary: A Client for Bkash API.
Home-page: https://gitlab.com/codesigntheory/python-bkash-client
Author: Utsob Roy
Author-email: roy@co.design
License: MIT
Project-URL: Documentation, https://python-bkash-client.readthedocs.io/
Project-URL: Changelog, https://python-bkash-client.readthedocs.io/en/latest/changelog.html
Project-URL: Issue Tracker, https://gitlab.com/codesigntheory/python-bkash-client/issues
Classifier: Development Status :: 5 - Production/Stable
Classifier: Intended Audience :: Developers
Classifier: License :: OSI Approved :: Mozilla Public License 2.0 (MPL 2.0)
Classifier: Operating System :: Unix
Classifier: Operating System :: POSIX
Classifier: Operating System :: Microsoft :: Windows
Classifier: Programming Language :: Python
Classifier: Programming Language :: Python :: 3
Classifier: Programming Language :: Python :: 3 :: Only
Classifier: Programming Language :: Python :: 3.6
Classifier: Programming Language :: Python :: 3.7
Classifier: Programming Language :: Python :: 3.8
Classifier: Programming Language :: Python :: 3.9
Classifier: Programming Language :: Python :: Implementation :: CPython
Classifier: Programming Language :: Python :: Implementation :: PyPy
Classifier: Topic :: Utilities
Requires-Python: >=3.6
License-File: LICENSE
License-File: AUTHORS.rst
Requires-Dist: pydantic
Requires-Dist: requests
